baklabel/__init__.py
baklabel/baklabel.py
baklabel/test_baklabel.py
baklabel-1.2.3.dist-info/METADATA
baklabel-1.2.3.dist-info/WHEEL
baklabel-1.2.3.dist-info/licenses/LICENSE
baklabel-1.2.3.dist-info/RECORD
