Metadata-Version: 2.1
Name: baklabel
Version: 1.2.3
Summary: Baklabel delivers a daily label fragment for grandfathered backups
Project-URL: Homepage, https://svn.climate.com.au/repos/pysrc/foss/baklabel
Author-email: Mike Dewhirst <miked@dewhirst.com.au>
License-File: LICENSE
Classifier: License :: OSI Approved :: MIT License
Classifier: Operating System :: OS Independent
Classifier: Programming Language :: Python :: 3
Requires-Python: >=3.8
